aoc_data_structures/__init__.py
aoc_data_structures/data_structures/__init__.py
aoc_data_structures/data_structures/integer_set.py
aoc_data_structures/data_structures/interval.py
aoc_data_structures/data_structures/vector_tuple.py
aoc_data_structures/grid_helpers.py
aoc_data_structures-0.0.6.dist-info/METADATA
aoc_data_structures-0.0.6.dist-info/WHEEL
aoc_data_structures-0.0.6.dist-info/RECORD
