Metadata-Version: 2.4
Name: aoc-data-structures
Version: 0.0.6
Summary: 
Author: Justin
Author-email: 18606523+jlewis200@users.noreply.github.com
Requires-Python: >=3.10,<4.0
Classifier: Programming Language :: Python :: 3
Classifier: Programming Language :: Python :: 3.10
Classifier: Programming Language :: Python :: 3.11
Classifier: Programming Language :: Python :: 3.12
Classifier: Programming Language :: Python :: 3.13
Classifier: Programming Language :: Python :: 3.14
Requires-Dist: numpy (>=2.0.0,<3.0.0)
Requires-Dist: sortedcontainers (>=2.4.0,<3.0.0)
